etlrules/__init__.py
etlrules/data.py
etlrules/engine.py
etlrules/exceptions.py
etlrules/plan.py
etlrules/rule.py
etlrules/runner.py
etlrules-0.3.3.dist-info/AUTHORS.md
etlrules-0.3.3.dist-info/LICENSE
etlrules-0.3.3.dist-info/METADATA
etlrules-0.3.3.dist-info/WHEEL
etlrules-0.3.3.dist-info/top_level.txt
etlrules-0.3.3.dist-info/RECORD
