Metadata-Version: 2.1
Name: etlrules
Version: 0.3.3
Summary: A python ETL rule engine operating with data frames.
Author-email: Ciprian Miclaus <ciprianm@gmail.com>
License: MIT License
Project-URL: homepage, https://github.com/ciprianmiclaus2/etlrules
Project-URL: documentation, https://ciprianmiclaus2.github.io/etlrules/
Project-URL: repository, https://github.com/ciprianmiclaus2/etlrules
Project-URL: history, https://github.com/ciprianmiclaus2/etlrules/blob/main/HISTORY.md
Classifier: Development Status :: 4 - Beta
Classifier: Intended Audience :: Developers
Classifier: License :: OSI Approved :: MIT License
Classifier: Natural Language :: English
Classifier: Programming Language :: Python :: 3
Classifier: Programming Language :: Python :: 3.9
Classifier: Programming Language :: Python :: 3.10
Classifier: Programming Language :: Python :: 3.11
Classifier: Programming Language :: Python :: 3.12
Requires-Python: >=3.9
License-File: LICENSE
License-File: AUTHORS.md
Requires-Dist: pandas >2
Requires-Dist: pyyaml >=6.0.1
Requires-Dist: pyarrow >=13.0.0
Requires-Dist: sqlalchemy >=2.0.0
Provides-Extra: dask
Requires-Dist: aiohttp ; extra == 'dask'
Requires-Dist: dask ; extra == 'dask'
Requires-Dist: requests ; extra == 'dask'
Provides-Extra: dev
Requires-Dist: tox ; extra == 'dev'
Requires-Dist: pre-commit ; extra == 'dev'
Requires-Dist: virtualenv ; extra == 'dev'
Requires-Dist: pip ; extra == 'dev'
Requires-Dist: twine ; extra == 'dev'
Requires-Dist: toml ; extra == 'dev'
Provides-Extra: docs
Requires-Dist: mkdocs ==1.5.3 ; extra == 'docs'
Requires-Dist: mkdocs-include-markdown-plugin ==3.9.1 ; extra == 'docs'
Requires-Dist: mkdocs-material ==8.1.11 ; extra == 'docs'
Requires-Dist: mkdocstrings ==0.18.1 ; extra == 'docs'
Requires-Dist: mkdocs-material-extensions ==1.3 ; extra == 'docs'
Requires-Dist: mkdocs-autorefs ==0.3.1 ; extra == 'docs'
Requires-Dist: mike ==1.1.2 ; extra == 'docs'
Provides-Extra: polars
Requires-Dist: polars >1 ; extra == 'polars'
Provides-Extra: test
Requires-Dist: pytest ; extra == 'test'
Requires-Dist: black ; extra == 'test'
Requires-Dist: isort ; extra == 'test'
Requires-Dist: flake8 ; extra == 'test'
Requires-Dist: flake8-docstrings ; extra == 'test'
Requires-Dist: pytest-cov ; extra == 'test'
